{
  "results": [
    {
      "address": {
        "country": "United States",
        "countryCode": "US",
        "countryCodeISO3": "USA",
        "countrySecondarySubdivision": "Chatham",
        "countrySubdivision": "GA",
        "countrySubdivisionName": "Georgia",
        "countryTertiarySubdivision": "Savannah",
        "extendedPostalCode": "314043724",
        "freeformAddress": "1901 East Victory Drive, Savannah, GA 31404",
        "localName": "Savannah",
        "municipality": "Savannah",
        "municipalitySubdivision": "Savannah, Dale Terrace-Olympus-Victory Square",
        "postalCode": "31404",
        "streetName": "East Victory Drive",
        "streetNumber": "1901"
      },
      "entryPoints": [
        {
          "position": {
            "lat": 32.04255,
            "lon": -81.0667
          },
          "type": "main"
        },
        {
          "position": {
            "lat": 32.04258,
            "lon": -81.06766
          },
          "type": "minor"
        },
        {
          "position": {
            "lat": 32.03972,
            "lon": -81.06513
          },
          "type": "minor"
        },
        {
          "position": {
            "lat": 32.0388,
            "lon": -81.06569
          },
          "type": "minor"
        },
        {
          "position": {
            "lat": 32.04204,
            "lon": -81.06593
          },
          "type": "minor"
        }
      ],
      "id": "US/PAD/p0/42201534",
      "position": {
        "lat": 32.04164,
        "lon": -81.06731
      },
      "score": 14.14995,
      "type": "Point Address",
      "viewport": {
        "btmRightPoint": {
          "lat": 32.04074,
          "lon": -81.06625
        },
        "topLeftPoint": {
          "lat": 32.04254,
          "lon": -81.06837
        }
      }
    },
    {
      "address": {
        "country": "United States",
        "countryCode": "US",
        "countryCodeISO3": "USA",
        "countrySecondarySubdivision": "Chatham",
        "countrySubdivision": "GA",
        "countrySubdivisionName": "Georgia",
        "countryTertiarySubdivision": "Savannah",
        "extendedPostalCode": "314043728, 314043900, 314043920, 314043922, 314043944, 314043945, 314043946, 314043947, 314043956, 314043957, 314043958, 314043959, 314043960, 314043961, 314043962, 314043963, 314043964, 314043965, 314043966, 314043967, 314043968, 314043969, 314043970, 314043971, 314043972, 314043988, 314046703, 314046705",
        "freeformAddress": "East Victory Drive, Savannah, GA 31404",
        "municipality": "Savannah",
        "municipalitySubdivision": "Savannah, Victory Heights",
        "postalCode": "31404",
        "streetName": "East Victory Drive"
      },
      "id": "US/STR/p0/4141525",
      "position": {
        "lat": 32.03831,
        "lon": -81.05929
      },
      "score": 12.44169,
      "type": "Street",
      "viewport": {
        "btmRightPoint": {
          "lat": 32.03685,
          "lon": -81.05689
        },
        "topLeftPoint": {
          "lat": 32.03985,
          "lon": -81.06189
        }
      }
    },
    {
      "address": {
        "country": "United States",
        "countryCode": "US",
        "countryCodeISO3": "USA",
        "countrySecondarySubdivision": "Chatham",
        "countrySubdivision": "GA",
        "countrySubdivisionName": "Georgia",
        "countryTertiarySubdivision": "Savannah",
        "extendedPostalCode": "3140400, 314040001, 314040002, 314040003, 314040004, 314041001, 314041002, 314041003, 314041004, 314041006, 314041055, 314041056, 314041070, 314043711, 314043713, 314043721, 314043726, 314043732, 314043733, 314043797, 314044100, 314044122, 314044124, 314044126, 314044128, 314044176, 314044177, 314044178, 314044195, 3140490, 314049000, 3140497, 314049700, 314049701, 314049702, 314049703, 314049704, 314049705, 314049706, 314049707, 314049708, 314049709, 314049710, 314049711, 314049712, 314049713, 314049714, 314049715, 314049716, 314049717, 314049718, 314049719, 314049720, 314049721, 314049722, 314049723, 314049724, 314049725, 314049726, 314049727, 314049728, 314049729, 314049730, 314049731, 314049732, 314049733, 314049734, 314049735, 314049737, 314049738, 314049739, 314049740, 314049741, 314049742, 3140499, 314049998, 3141477, 314147700, 314147701, 314147702, 314147703, 314147704, 314147705, 314147706, 314147707, 314147708, 314147709, 314147710, 314147711, 314147712, 314147713, 314147714, 314147715, 314147716, 314147717, 314147718, 314147719, 314147720, 314147721, 314147722, 314147723, 314147724, 314147725, 314147726, 314147727, 314147728, 314147729, 314147730, 314147731, 314147732, 314147733, 314147734, 314147735, 314147736, 314147737, 314147738, 314147739, 314147740, 314147741, 314147742, 314147743, 314147744, 314147745, 314147746, 314147747, 314147748, 314147749, 314147750, 314147751, 314147752, 314147753, 314147754, 314147755, 314147756, 314147757, 314147758, 314147759, 314147760, 314147761, 314147762, 314147763, 314147764, 314147765, 314147766, 314147767, 314147768, 314147769, 314147770, 314147771, 314147772, 314147773, 314147774, 314147775, 314147776, 314147777, 314147778, 314147779, 314147780, 314147781, 314147782, 314147783, 314147784, 314147785",
        "freeformAddress": "East Victory Drive, Savannah, GA",
        "municipality": "Savannah",
        "municipalitySubdivision": "Savannah, Victory Manor-East Hill-Donwood, Dale Terrace-Olympus-Victory Square",
        "postalCode": "31404, 31414",
        "streetName": "East Victory Drive"
      },
      "id": "US/STR/p0/5803299",
      "position": {
        "lat": 32.04448,
        "lon": -81.07177
      },
      "score": 12.44169,
      "type": "Street",
      "viewport": {
        "btmRightPoint": {
          "lat": 32.04296,
          "lon": -81.06733
        },
        "topLeftPoint": {
          "lat": 32.04584,
          "lon": -81.07662
        }
      }
    },
    {
      "address": {
        "country": "United States",
        "countryCode": "US",
        "countryCodeISO3": "USA",
        "countrySecondarySubdivision": "Chatham",
        "countrySubdivision": "GA",
        "countrySubdivisionName": "Georgia",
        "countryTertiarySubdivision": "Savannah",
        "extendedPostalCode": "314044102, 314044104, 314044106, 314044108, 314044141, 314044142, 314044143, 314044144, 314044145, 314044146, 314044147, 314044148, 314044149, 314044150, 314044151, 314044152, 314044153, 314044154, 314044157, 314044159, 314044160, 314044161, 314044162, 314044163, 314044164, 314044165, 314044166, 314044167, 314044168, 314044169, 314044170, 314044171, 314044196, 314044197, 314044198, 314044199",
        "freeformAddress": "East Victory Drive, Savannah, GA 31404",
        "municipality": "Savannah",
        "municipalitySubdivision": "Savannah, Parkside, Live Oak",
        "postalCode": "31404",
        "streetName": "East Victory Drive"
      },
      "id": "US/STR/p0/6925947",
      "position": {
        "lat": 32.04716,
        "lon": -81.08131
      },
      "score": 12.44169,
      "type": "Street",
      "viewport": {
        "btmRightPoint": {
          "lat": 32.04584,
          "lon": -81.07662
        },
        "topLeftPoint": {
          "lat": 32.0483,
          "lon": -81.08526
        }
      }
    }
  ],
  "search_address": "1901 E Victory Dr Savannah GA 31404",
  "summary": {
    "fuzzyLevel": 1,
    "numResults": 4,
    "offset": 0,
    "query": "1901 e victory dr savannah ga 31404",
    "queryTime": 221,
    "queryType": "NON_NEAR",
    "totalResults": 42
  }
}